README.rst
setup.cfg
setup.py
ether_examples/__init__.py
ether_examples/decrypt_utc.py
ether_examples.egg-info/PKG-INFO
ether_examples.egg-info/SOURCES.txt
ether_examples.egg-info/dependency_links.txt
ether_examples.egg-info/entry_points.txt
ether_examples.egg-info/requires.txt
ether_examples.egg-info/top_level.txt
tests/__init__.py
tests/test_decrypt_wallet.py