Metadata-Version: 1.1
Name: ether-examples
Version: 0.2.1
Summary: Learn Ethereum by examples
Home-page: https://github.com/VISCHub/ether-examples
Author: Viet Le
Author-email: vietlq85@gmail.com
License: UNKNOWN
Keywords: ethereum cryptography examples
Platform: UNKNOWN
Classifier: Development Status :: 3 - Alpha
Classifier: Environment :: Console
Classifier: Intended Audience :: Developers
Classifier: License :: OSI Approved :: Apache Software License
Classifier: Operating System :: OS Independent
Classifier: Programming Language :: Python
Classifier: Programming Language :: Python :: 3
Classifier: Programming Language :: Python :: 3.6
Classifier: Programming Language :: Python :: 3.7
Classifier: Programming Language :: Python :: 3.8
Classifier: Programming Language :: Python :: 3.9
Classifier: Topic :: Software Development :: Libraries :: Python Modules
